Metadata-Version: 2.1
Name: gandalf-cmt
Version: 1.2.26
Summary: Gandalf is a Configuration Management tool.
Home-page: UNKNOWN
Author: Arjun Babu
Author-email: arbnair97@gmail.com
Maintainer: Arjun Babu
Maintainer-email: arbnair97@gmail.com
License: MIT
Keywords: gandalf-cmt
Platform: UNKNOWN
Classifier: Development Status :: 5 - Production/Stable
